BuildBinary.py
AlpineHtmxWebViewTest/Api.py
AlpineHtmxWebViewTest/EntryPoint.py
AlpineHtmxWebViewTest/Server.py
AlpineHtmxWebViewTest/__init__.py
AlpineHtmxWebViewTest-0.1.7.dist-info/LICENSE.txt
AlpineHtmxWebViewTest-0.1.7.dist-info/METADATA
AlpineHtmxWebViewTest-0.1.7.dist-info/WHEEL
AlpineHtmxWebViewTest-0.1.7.dist-info/entry_points.txt
AlpineHtmxWebViewTest-0.1.7.dist-info/top_level.txt
AlpineHtmxWebViewTest-0.1.7.dist-info/RECORD
