Metadata-Version: 2.1
Name: AlpineHtmxWebViewTest
Version: 0.1.7
Summary: Test repo for a solution that uses Alpine.js, HTMX, and pywebview.
Author-email: David Brownell <db@DavidBrownell.com>
License: MIT
Project-URL: Homepage, https://github.com/davidbrownell/AlpineHtmxWebViewTest
Project-URL: Documentation, https://github.com/davidbrownell/AlpineHtmxWebViewTest
Project-URL: Repository, https://github.com/davidbrownell/AlpineHtmxWebViewTest
Classifier: License :: OSI Approved :: MIT License
Classifier: Operating System :: MacOS
Classifier: Operating System :: Microsoft :: Windows
Classifier: Operating System :: POSIX :: Linux
Classifier: Programming Language :: Python
Classifier: Programming Language :: Python :: 3.10
Classifier: Programming Language :: Python :: 3.11
Classifier: Programming Language :: Python :: 3.12
License-File: LICENSE.txt
Requires-Dist: bleach ==6.*
Requires-Dist: cryptography ==42.*
Requires-Dist: dbrownell-Common
Requires-Dist: flask ==3.*
Requires-Dist: pywebview ==5.*
Requires-Dist: typer ~=0.9
Provides-Extra: dev
Requires-Dist: dbrownell-DevTools ; extra == 'dev'
Provides-Extra: package
Requires-Dist: build ==1.* ; extra == 'package'
Requires-Dist: cx-Freeze ==6.* ; extra == 'package'
Requires-Dist: twine ==4.* ; extra == 'package'
